README.rst
setup.cfg
setup.py
tensorly/__init__.py
tensorly/base.py
tensorly/kruskal_tensor.py
tensorly/mps_tensor.py
tensorly/testing.py
tensorly/tucker_tensor.py
tensorly/backend/__init__.py
tensorly/backend/core.py
tensorly/backend/cupy_backend.py
tensorly/backend/mxnet_backend.py
tensorly/backend/numpy_backend.py
tensorly/backend/pytorch_backend.py
tensorly/backend/tensorflow_backend.py
tensorly/contrib/__init__.py
tensorly/contrib/decomposition/__init__.py
tensorly/contrib/decomposition/mps_decomposition_cross.py
tensorly/contrib/decomposition/tests/__init__.py
tensorly/contrib/decomposition/tests/test_mps_decomposition_cross.py
tensorly/contrib/sparse/__init__.py
tensorly/contrib/sparse/core.py
tensorly/contrib/sparse/decomposition.py
tensorly/contrib/sparse/kruskal_tensor.py
tensorly/contrib/sparse/tenalg.py
tensorly/contrib/sparse/backend/__init__.py
tensorly/contrib/sparse/backend/numpy_backend.py
tensorly/contrib/sparse/tests/__init__.py
tensorly/contrib/sparse/tests/test_decomposition.py
tensorly/contrib/sparse/tests/test_tenalg.py
tensorly/datasets/__init__.py
tensorly/datasets/synthetic.py
tensorly/datasets/tests/__init__.py
tensorly/datasets/tests/test_synthetic.py
tensorly/decomposition/__init__.py
tensorly/decomposition/_tucker.py
tensorly/decomposition/candecomp_parafac.py
tensorly/decomposition/mps_decomposition.py
tensorly/decomposition/robust_decomposition.py
tensorly/decomposition/tests/__init__.py
tensorly/decomposition/tests/test_candecomp_parafac.py
tensorly/decomposition/tests/test_mps_decomposition.py
tensorly/decomposition/tests/test_robust_decomposition.py
tensorly/decomposition/tests/test_tucker.py
tensorly/metrics/__init__.py
tensorly/metrics/regression.py
tensorly/metrics/tests/__init__.py
tensorly/metrics/tests/test_regression.py
tensorly/random/__init__.py
tensorly/random/base.py
tensorly/random/tests/__init__.py
tensorly/random/tests/test_base.py
tensorly/regression/__init__.py
tensorly/regression/kruskal_regression.py
tensorly_musco.egg-info/PKG-INFO
tensorly_musco.egg-info/SOURCES.txt
tensorly_musco.egg-info/dependency_links.txt
tensorly_musco.egg-info/requires.txt
tensorly_musco.egg-info/top_level.txt