Metadata-Version: 2.1
Name: tensorly-musco
Version: 0.4.5
Summary: Tensor learning in Python.
Home-page: UNKNOWN
Author: Jean Kossaifi
Author-email: jean.kossaifi@gmail.com
License: Modified BSD
Platform: UNKNOWN
Classifier: Topic :: Scientific/Engineering
Classifier: License :: OSI Approved :: BSD License
Classifier: Programming Language :: Python :: 3
